binaexperts/__init__.py
binaexperts/SDKs/__init__.py
binaexperts/SDKs/YOLO/__init__.py
binaexperts/SDKs/YOLO/yolov5/__init__.py
binaexperts/SDKs/YOLO/yolov5/benchmarks.py
binaexperts/SDKs/YOLO/yolov5/detect.py
binaexperts/SDKs/YOLO/yolov5/export.py
binaexperts/SDKs/YOLO/yolov5/hubconf.py
binaexperts/SDKs/YOLO/yolov5/train.py
binaexperts/SDKs/YOLO/yolov5/val.py
binaexperts/SDKs/YOLO/yolov5/classify/__init__.py
binaexperts/SDKs/YOLO/yolov5/classify/predict.py
binaexperts/SDKs/YOLO/yolov5/classify/train.py
binaexperts/SDKs/YOLO/yolov5/classify/val.py
binaexperts/SDKs/YOLO/yolov5/models/__init__.py
binaexperts/SDKs/YOLO/yolov5/models/common.py
binaexperts/SDKs/YOLO/yolov5/models/experimental.py
binaexperts/SDKs/YOLO/yolov5/models/tf.py
binaexperts/SDKs/YOLO/yolov5/models/yolo.py
binaexperts/SDKs/YOLO/yolov5/segment/__init__.py
binaexperts/SDKs/YOLO/yolov5/segment/predict.py
binaexperts/SDKs/YOLO/yolov5/segment/train.py
binaexperts/SDKs/YOLO/yolov5/segment/val.py
binaexperts/SDKs/YOLO/yolov5/utils/__init__.py
binaexperts/SDKs/YOLO/yolov5/utils/activations.py
binaexperts/SDKs/YOLO/yolov5/utils/augmentations.py
binaexperts/SDKs/YOLO/yolov5/utils/autoanchor.py
binaexperts/SDKs/YOLO/yolov5/utils/autobatch.py
binaexperts/SDKs/YOLO/yolov5/utils/callbacks.py
binaexperts/SDKs/YOLO/yolov5/utils/dataloaders.py
binaexperts/SDKs/YOLO/yolov5/utils/downloads.py
binaexperts/SDKs/YOLO/yolov5/utils/general.py
binaexperts/SDKs/YOLO/yolov5/utils/loss.py
binaexperts/SDKs/YOLO/yolov5/utils/metrics.py
binaexperts/SDKs/YOLO/yolov5/utils/plots.py
binaexperts/SDKs/YOLO/yolov5/utils/torch_utils.py
binaexperts/SDKs/YOLO/yolov5/utils/triton.py
binaexperts/SDKs/YOLO/yolov5/utils/aws/__init__.py
binaexperts/SDKs/YOLO/yolov5/utils/aws/resume.py
binaexperts/SDKs/YOLO/yolov5/utils/flask_rest_api/__init__.py
binaexperts/SDKs/YOLO/yolov5/utils/flask_rest_api/example_request.py
binaexperts/SDKs/YOLO/yolov5/utils/flask_rest_api/restapi.py
binaexperts/SDKs/YOLO/yolov5/utils/loggers/__init__.py
binaexperts-0.6.0.dist-info/LICENSE
binaexperts-0.6.0.dist-info/METADATA
binaexperts-0.6.0.dist-info/WHEEL
binaexperts-0.6.0.dist-info/top_level.txt
binaexperts-0.6.0.dist-info/RECORD
