Metadata-Version: 2.1
Name: binaexperts
Version: 0.6.0
Summary: Binaexperts SDK, a comprehensive computer vision toolkit
Author: Nastaran Dab, Parsa Khanmohamadi
Author-email: n.dab@binaexperts.com, parsa.khmd@gmail.com
License: MIT
Classifier: Programming Language :: Python :: 3
Classifier: License :: OSI Approved :: MIT License
Classifier: Operating System :: OS Independent
Requires-Python: >=3.9
License-File: LICENSE
Requires-Dist: PyYAML==6.0.2
Requires-Dist: setuptools==68.2.0
Requires-Dist: requests
Requires-Dist: jsonschema==4.23.0
Requires-Dist: opencv-python==4.10.0.84
Requires-Dist: numpy==2.1.1
Provides-Extra: inference
Requires-Dist: torch>=2.0.0; extra == "inference"
Requires-Dist: torchvision; extra == "inference"
Requires-Dist: ultralytics; extra == "inference"
Requires-Dist: gitpython>=3.1.30; extra == "inference"
Requires-Dist: matplotlib>=3.8.0; extra == "inference"
Requires-Dist: pandas>=2.1.0; extra == "inference"
Requires-Dist: tqdm>=4.66.1; extra == "inference"
Requires-Dist: seaborn>=0.13.2; extra == "inference"
Requires-Dist: scipy>=1.12.0; extra == "inference"
